basewordle/__init__.py
basewordle/__main__.py
basewordle/code.py
basewordle/py.typed
basewordle/words/512.txt
basewordle/words/fives.txt
basewordle/words/foury.txt
basewordle/words/minus_27.txt
basewordle/words/minus_58.txt
basewordle-0.1.0.dist-info/METADATA
basewordle-0.1.0.dist-info/WHEEL
basewordle-0.1.0.dist-info/entry_points.txt
basewordle-0.1.0.dist-info/RECORD
