Metadata-Version: 2.1
Name: basewordle
Version: 0.1.0
Summary: 
Author: Peter Gaultney
Author-email: petergaultney@gmail.com
Requires-Python: >=3.8,<4.0
Classifier: Programming Language :: Python :: 3
Classifier: Programming Language :: Python :: 3.8
Classifier: Programming Language :: Python :: 3.9
Classifier: Programming Language :: Python :: 3.10
Classifier: Programming Language :: Python :: 3.11
